yaml_extras/__init__.py
yaml_extras/file_utils.py
yaml_extras/yaml_import.py
yaml_extras-0.2.2.dist-info/LICENSE
yaml_extras-0.2.2.dist-info/METADATA
yaml_extras-0.2.2.dist-info/WHEEL
yaml_extras-0.2.2.dist-info/RECORD
