Metadata-Version: 2.3
Name: yaml-extras
Version: 0.2.2
Summary: A collection of YAML utilities
Home-page: https://github.com/dsillman2000/yaml-extras.git
License: MIT
Keywords: yaml,yml,pyyaml,extras,yaml-extras
Author: David Sillman
Author-email: dsillman2000@gmail.com
Requires-Python: >=3.11,<4.0
Classifier: Development Status :: 4 - Beta
Classifier: Intended Audience :: Developers
Classifier: Topic :: Software Development :: Libraries :: Python Modules
Classifier: Topic :: File Formats
Classifier: Topic :: Utilities
Classifier: Programming Language :: Python :: 3.11
Classifier: Programming Language :: Python :: 3.12
Classifier: Programming Language :: Python :: 3.13
Requires-Dist: pyyaml (>=6.0.2,<7.0.0)
Project-URL: Documentation, https://yaml-extras.pages.dev/
Project-URL: Repository, https://github.com/dsillman2000/yaml-extras.git
